urmem/__init__.py
urmem/urmem.py
urmem-0.0.45.dist-info/METADATA
urmem-0.0.45.dist-info/WHEEL
urmem-0.0.45.dist-info/entry_points.txt
urmem-0.0.45.dist-info/top_level.txt
urmem-0.0.45.dist-info/RECORD
