Metadata-Version: 2.1
Name: urmem
Version: 0.0.45
Summary: Download a git repo raw file content in every server, sometimes for source bash_profile
Home-page: https://github.com/doomzhou/urmem
Author: doomzhou
Author-email: zzepaigh@gmail.com
License: Apache
Platform: UNKNOWN
